pydos2unix/__init__.py
pydos2unix/dos2unix.py
pydos2unix-0.0.1.dist-info/METADATA
pydos2unix-0.0.1.dist-info/WHEEL
pydos2unix-0.0.1.dist-info/licenses/LICENSE
pydos2unix-0.0.1.dist-info/RECORD
