Metadata-Version: 2.1
Name: pydos2unix
Version: 0.0.1
Summary: Convert DOS (CRLF) files to Unix (LF) files and vice vera, written in Python.
Project-URL: Homepage, https://github.com/dmcdo/pydos2unix
Author-email: Dylan McDougall <dylanalexandermcdougall@outlook.com>
License-Expression: MIT
License-File: LICENSE
Keywords: dos2unix,unix2dos
Classifier: License :: OSI Approved :: MIT License
Classifier: Operating System :: OS Independent
Classifier: Programming Language :: Python :: 3
Requires-Python: >=3.8
